bew/__init__.py
bew_wp-0.0.1.dist-info/LICENSE
bew_wp-0.0.1.dist-info/METADATA
bew_wp-0.0.1.dist-info/WHEEL
bew_wp-0.0.1.dist-info/top_level.txt
bew_wp-0.0.1.dist-info/RECORD
