Metadata-Version: 2.1
Name: bew-wp
Version: 0.0.1
Summary: A very easy tool to publish Markdown post to your WordPress website
Home-page: https://github.com/JinhangZhu/bew
Author: Jinhang
Author-email: jinhang.d.zhu@gmail.com
License: UNKNOWN
Platform: UNKNOWN
Classifier: Programming Language :: Python :: 3
Classifier: License :: OSI Approved :: MIT License
Classifier: Operating System :: OS Independent
Requires-Python: >=3.6
